rcfc/__init__.py
rcfc/button.py
rcfc/demo.py
rcfc/groups.py
rcfc/input_methods.py
rcfc/server.py
rcfc/static/index.html
rcfc/static/index.js
rcfc/static/static.css
rcfc-1.2.0.dist-info/DESCRIPTION.rst
rcfc-1.2.0.dist-info/METADATA
rcfc-1.2.0.dist-info/RECORD
rcfc-1.2.0.dist-info/WHEEL
rcfc-1.2.0.dist-info/entry_points.txt
rcfc-1.2.0.dist-info/metadata.json
rcfc-1.2.0.dist-info/top_level.txt
