Metadata-Version: 2.0
Name: rcfc
Version: 1.2.0
Summary: A framework that gives a remote control for any Python function you want to run on a computer
Home-page: http://github.com/pviafore/rcfc
Author: Pat Viafore
Author-email: patviafore+rcfc@gmail.com
License: MIT
Platform: UNKNOWN
Requires-Python: >=3.6
Requires-Dist: bottle
